{
  "settings": {
    "migrated": 6,
    "iconPacksPath": ".obsidian/icons",
    "fontSize": 16,
    "emojiStyle": "native",
    "iconColor": null,
    "recentlyUsedIcons": [
      "LiOctagon",
      "LiRectangleHorizontal",
      "LiUser2",
      "LiSword",
      "LiBook"
    ],
    "recentlyUsedIconsSize": 5,
    "rules": [],
    "extraMargin": {
      "top": 0,
      "right": 4,
      "bottom": 0,
      "left": 0
    },
    "iconInTabsEnabled": false,
    "iconInTitleEnabled": true,
    "iconInFrontmatterEnabled": true,
    "iconsBackgroundCheckEnabled": false,
    "iconsInNotesEnabled": true,
    "iconIdentifier": ":",
    "iconInTitlePosition": "inline",
    "iconInFrontmatterFieldName": "icon",
    "iconColorInFrontmatterFieldName": "iconColor",
    "iconsInLinksEnabled": true,
    "lucideIconPackType": "native",
    "debugMode": false,
    "useInternalPlugins": false
  },
  "Campaigns/Example_Campaign/World/Establisments/Shop ang gibbles.md": {
    "iconName": "LiStore"
  },
  "Configuations/Templates/Template_PC.md": {
    "iconName": "LiSwords",
    "iconColor": "blue"
  },
  "Configuations/Templates/Template_Quest.md": {
    "iconName": "LiHandCoins",
    "iconColor": "yellow"
  },
  "Configuations/Templates/Template_NPC.md": {
    "iconName": "LiUser",
    "iconColor": "green"
  },
  "Configuations/Templates/Template_Lore.md": {
    "iconName": "LiBook",
    "iconColor": "yellow"
  },
  "Configuations/Templates/Template_Inventory.md": {
    "iconName": "LiSword",
    "iconColor": "orange"
  },
  "Configuations/Templates/Template_Faction.md": {
    "iconName": "LiUser2",
    "iconColor": "purple"
  },
  "Configuations/Templates/Template_Campaign_Manager.md": {
    "iconName": "LiBookOpen"
  },
  "Configuations/Templates/Template_Session.md": {
    "iconName": "LiBookA",
    "iconColor": "red"
  },
  "Campaigns/Example_Campaign/World/Locations/Forterra 2.md": {
    "iconName": "LiRectangleHorizontal",
    "iconColor": "blue"
  }
}